MANIFEST.in
README.md
setup.cfg
setup.py
inc_package_manager/.version
inc_package_manager/__init__.py
inc_package_manager/__main__.py
inc_package_manager/manage.py
inc_package_manager.egg-info/PKG-INFO
inc_package_manager.egg-info/SOURCES.txt
inc_package_manager.egg-info/dependency_links.txt
inc_package_manager.egg-info/not-zip-safe
inc_package_manager.egg-info/top_level.txt
inc_package_manager/__defaults__/django/__init__.py
inc_package_manager/__defaults__/django/asgi.py
inc_package_manager/__defaults__/django/settings.py
inc_package_manager/__defaults__/django/urls.py
inc_package_manager/__defaults__/django/wsgi.py
inc_package_manager/__defaults__/static/._favicon.icns
inc_package_manager/__defaults__/static/favicon.icns
inc_package_manager/__defaults__/static/favicon.ico
inc_package_manager/__defaults__/static/favicon.png
inc_package_manager/__defaults__/static/media/graphics/icon.icns
inc_package_manager/__defaults__/static/media/graphics/icon.ico
inc_package_manager/__defaults__/static/media/graphics/icon.jpg
inc_package_manager/__defaults__/static/media/graphics/icon.png
inc_package_manager/__defaults__/static/media/icons/cancel.png
inc_package_manager/__defaults__/static/media/icons/check.png
inc_package_manager/__defaults__/static/media/icons/warning.png
inc_package_manager/__defaults__/static/media/icons/blue/add_1.png
inc_package_manager/__defaults__/static/media/icons/blue/add_2.png
inc_package_manager/__defaults__/static/media/icons/blue/arrow_up.png
inc_package_manager/__defaults__/static/media/icons/blue/base_circle.png
inc_package_manager/__defaults__/static/media/icons/blue/exit.png
inc_package_manager/__defaults__/static/media/icons/blue/folder-user.png
inc_package_manager/__defaults__/static/media/icons/blue/folder.png
inc_package_manager/__defaults__/static/media/icons/blue/folder_2.png
inc_package_manager/__defaults__/static/media/icons/blue/folder_3.png
inc_package_manager/__defaults__/static/media/icons/blue/folder_network.png
inc_package_manager/__defaults__/static/media/icons/blue/graph_1.png
inc_package_manager/__defaults__/static/media/icons/blue/graph_2.png
inc_package_manager/__defaults__/static/media/icons/blue/graph_3.png
