Metadata-Version: 1.0
Name: inc-package-manager
Version: 2.21.3
Summary: Some description.
Home-page: http://github.com/vandenberghinc/vandenberghinc-package-manager
Author: Daan van den Bergh
Author-email: vandenberghinc.contact@gmail.com
License: MIT
Platform: UNKNOWN
